pdf_tools/__init__.py
pdf_tools/cli/__init__.py
pdf_tools/cli/async_typer.py
pdf_tools/convert/__init__.py
pdf_tools/convert/cli.py
pdf_tools/convert/service.py
pdf_tools/convert/unoserver_ctx.py
pdf_tools/main.py
pdf_tools/merge/__init__.py
pdf_tools/merge/cli.py
pdf_tools/merge/service.py
pdf_tools/models/__init__.py
pdf_tools/models/files.py
pdf_tools/models/watermark.py
pdf_tools/process/__init__.py
pdf_tools/process/cli.py
pdf_tools/process/service.py
pdf_tools/typings.py
pdf_tools/watermark/__init__.py
pdf_tools/watermark/cli.py
pdf_tools/watermark/service.py
pdf_toolchest-0.1.13.dist-info/LICENSE
pdf_toolchest-0.1.13.dist-info/METADATA
pdf_toolchest-0.1.13.dist-info/WHEEL
pdf_toolchest-0.1.13.dist-info/entry_points.txt
pdf_toolchest-0.1.13.dist-info/RECORD
