Metadata-Version: 2.3
Name: pdf-toolchest
Version: 0.1.13
Summary: A Swiss-army knife for everyday PDF workflows – pure-Python, cross-platform, and fully typed.
Author: Alex
Author-email: aswann@protonmail.com
Requires-Python: <4,>=3.11
Classifier: Programming Language :: Python :: 3
Classifier: Programming Language :: Python :: 3.11
Classifier: Programming Language :: Python :: 3.12
Classifier: Programming Language :: Python :: 3.13
Requires-Dist: coverage (>=7.9.2,<8.0.0)
Requires-Dist: hypothesis (>=6.136.3,<7.0.0)
Requires-Dist: img2pdf (>=0.5.1,<0.6.0)
Requires-Dist: pillow (>=11.1.0,<12.0.0)
Requires-Dist: pydantic (>=2.10.6,<3.0.0)
Requires-Dist: pymupdf (>=1.26.3,<2.0.0)
Requires-Dist: pypdf (>=5.2.0,<6.0.0)
Requires-Dist: pytest (>=8.4.1,<9.0.0)
Requires-Dist: reportlab (>=4.4.3,<5.0.0)
Requires-Dist: typer (>=0.15.1,<0.16.0)
Requires-Dist: types-reportlab (>=4.4.1.20250602,<5.0.0.0)
